[
    {
        "name": "Turael",
        "perTask": 0,
        "per10": 0,
        "per50": 0,
        "per100": 0,
        "per250": 0,
        "per1000": 0
    },
    {
        "name": "Mazchna",
        "perTask": 2,
        "per10": 5,
        "per50": 15,
        "per100": 50,
        "per250": 70,
        "per1000": 100
    },
    {
        "name": "Vannaka",
        "perTask": 4,
        "per10": 20,
        "per50": 60,
        "per100": 100,
        "per250": 140,
        "per1000": 200
    },
    {
        "name": "Chaeldar",
        "perTask": 10,
        "per10": 50,
        "per50": 150,
        "per100": 250,
        "per250": 350,
        "per1000": 500
    },
    {
        "name": "Nieve/Steve",
        "perTask": 12,
        "per10": 60,
        "per50": 180,
        "per100": 300,
        "per250": 420,
        "per1000": 600 
    },
    {
        "name": "Duradel/Steve with Elite Western Diaries",
        "perTask": 15,
        "per10": 75,
        "per50": 225,
        "per100": 375,
        "per250": 525,
        "per1000": 750
    },
    {
        "name": "Krystilia",
        "perTask": 25,
        "per10": 125,
        "per50": 375,
        "per100": 625,
        "per250": 875,
        "per1000": 1250
    }
]